ml_agreement/__init__.py
ml_agreement/ml_agreement.py
ml_agreement-1.0.2.dist-info/licenses/LICENSE
ml_agreement-1.0.2.dist-info/METADATA
ml_agreement-1.0.2.dist-info/WHEEL
ml_agreement-1.0.2.dist-info/top_level.txt
ml_agreement-1.0.2.dist-info/RECORD
