Metadata-Version: 2.4
Name: ml_agreement
Version: 1.0.2
Summary: A metric to calculate inter-annotator agreement for scenarios where several labels can be simultaneously assigned to an item
Home-page: https://github.com/Timperator2/MultiLabelAgreement
Author: Tim Menzner
Author-email: tim.menzner@hs-coburg.de
Requires-Python: >=3.6
License-File: LICENSE
Dynamic: author
Dynamic: author-email
Dynamic: description
Dynamic: description-content-type
Dynamic: home-page
Dynamic: license-file
Dynamic: requires-python
Dynamic: summary
